particleShear/__init__.py
particleShearBase/CanvasPoints.py
particleShearBase/CanvasPointsBasicElasticity.py
particleShearBase/CanvasPointsBasicElasticityLeesEdwards.py
particleShearBase/CanvasPointsFrictionElasticityLeesEdwards.py
particleShearBase/CanvasPointsMass.py
particleShearBase/CanvasPointsNeighbors.py
particleShearBase/CanvasPointsShear.py
particleShearBase/Circle.py
particleShearBase/CircleBasicElasticity.py
particleShearBase/CircleFrictionElasticity.py
particleShearBase/CircleMass.py
particleShearBase/CircleMassNeighbors.py
particleShearBase/Force_register.py
particleShearBase/Graphical_output_configuration.py
particleShearBase/Point.py
particleShearBase/PointLeesEdwards.py
particleShearBase/StressTensorEvaluation.py
particleShearBase/__init__.py
particleShearBase/neighbor_relation.py
particleShearLinkableObjects/CanvasPointsLinkable.py
particleShearLinkableObjects/EnsembleCompactParticles.py
particleShearLinkableObjects/EnsembleCompactParticlesAdjustableInterfaceStrength.py
particleShearLinkableObjects/EnsembleLinkable.py
particleShearLinkableObjects/SphereLinkable.py
particleShearLinkableObjects/SphereLinkableAdjustableInterfaceStrength.py
particleShearLinkableObjects/__init__.py
particleShearLinkableObjects/neighbor_relation_linkable.py
particleShearObjects/Ensemble.py
particleShearObjects/EnsembleFriction.py
particleShearObjects/EnsembleFrictionLeesEdwards.py
particleShearObjects/EnsembleLeesEdwards.py
particleShearObjects/Sphere.py
particleShearObjects/SphereFriction.py
particleShearObjects/SphereFrictionLeesEdwards.py
particleShearObjects/SphereLeesEdwards.py
particleShearObjects/__init__.py
particleShearObjects/particle_shear_model_parameters.py
particleShearRunSimulation/__init__.py
particleShearRunSimulation/doParticleShearSimulation.py
particleShearRunSimulation/doParticleShearSimulationSeries.py
particleShearSimulation/EvaluationHandler.py
particleShearSimulation/EvaluationHandlerPlotter.py
particleShear-1.0.2.dist-info/LICENSE
particleShear-1.0.2.dist-info/METADATA
particleShear-1.0.2.dist-info/WHEEL
particleShear-1.0.2.dist-info/top_level.txt
particleShear-1.0.2.dist-info/RECORD
