Metadata-Version: 2.1
Name: particleShear
Version: 1.0.2
Summary: Simulation of frictional and possibly crosslinked particles in shear
Home-page: https://github.com/tbgitoo/particleShear
Author: Thomas Braschler
Author-email: thomas.braschler@unige.ch
License: MIT
Project-URL: Bug Tracker, https://github.com/tbgitoo/particleShear/issues
Platform: UNKNOWN
Classifier: Development Status :: 4 - Beta
Classifier: Programming Language :: Python :: 3
Classifier: License :: OSI Approved :: GNU General Public License v3 or later (GPLv3+)
Classifier: Operating System :: OS Independent
Requires-Python: >=3.5
Requires-Dist: Pillow
